mongotree.py
mongotree-0.1.3.dist-info/DESCRIPTION.rst
mongotree-0.1.3.dist-info/METADATA
mongotree-0.1.3.dist-info/RECORD
mongotree-0.1.3.dist-info/WHEEL
mongotree-0.1.3.dist-info/metadata.json
mongotree-0.1.3.dist-info/top_level.txt
