Metadata-Version: 2.0
Name: mongotree
Version: 0.1.3
Summary: Python module for tree structures in MongoDB
Home-page: https://github.com/JoelBender/mongotree
Author: Joel Bender
Author-email: joel@carrickbender.com
License: MIT
Keywords: mongotree
Platform: UNKNOWN
Classifier: Development Status :: 2 - Pre-Alpha
Classifier: Intended Audience :: Developers
Classifier: License :: OSI Approved :: MIT License
Classifier: Natural Language :: English
Classifier: Programming Language :: Python :: 2
Classifier: Programming Language :: Python :: 2.7
Classifier: Programming Language :: Python :: 3
Classifier: Programming Language :: Python :: 3.4
Requires-Dist: pymongo
